cat_ai/__init__.py
cat_ai/helpers/__init__.py
cat_ai/helpers/helpers.py
cat_ai/reporter.py
cat_ai/runner.py
cat_ai/validator.py
cat_ai-0.0.5a0.dist-info/METADATA
cat_ai-0.0.5a0.dist-info/WHEEL
cat_ai-0.0.5a0.dist-info/RECORD
