Metadata-Version: 2.3
Name: cat-ai
Version: 0.0.5a0
Summary: Python client for running CAT tests in a Python codebase
Author: Mike Gehard
Author-email: mikegehard@artium.ai
Requires-Python: >=3.12,<4.0
Classifier: Programming Language :: Python :: 3
Classifier: Programming Language :: Python :: 3.12
Classifier: Programming Language :: Python :: 3.13
Requires-Dist: pydantic (>=2.10.6,<3.0.0)
